{
    "data": [{
        "index": 5,
        "itemname": "OUTPUT",
        "children": [{
            "value": 211067.047331678,
            "date": "2017-06-30"
        }, {
            "value": 198576.981660531,
            "date": "2017-07-31"
        }, {
            "value": 207706.428760892,
            "date": "2017-08-31"
        }, {
            "value": 214073.385932067,
            "date": "2017-09-30"
        }, {
            "value": 195616.489058909,
            "date": "2017-10-31"
        }, {
            "value": 199713.510519644,
            "date": "2017-11-30"
        }, {
            "value": 216909.185516465,
            "date": "2017-12-31"
        }, {
            "value": 183359.522628008,
            "date": "2018-01-31"
        }, {
            "value": 183757.187411113,
            "date": "2018-02-28"
        }, {
            "value": 204658.84934687,
            "date": "2018-03-31"
        }, {
            "value": 194162.800967695,
            "date": "2018-04-30"
        }, {
            "value": 204291.178121943,
            "date": "2018-05-31"
        }],
        "itemid": 1093000005,
        "type": 9
    }, {
        "index": 8,
        "itemname": "OPI",
        "children": [{
            "value": 48871.032945536,
            "date": "2017-06-30"
        }, {
            "value": 37394.475920134,
            "date": "2017-07-31"
        }, {
            "value": 37051.676915907,
            "date": "2017-08-31"
        }, {
            "value": 41871.657288541,
            "date": "2017-09-30"
        }, {
            "value": 39136.697326269,
            "date": "2017-10-31"
        }, {
            "value": 36616.687795435,
            "date": "2017-11-30"
        }, {
            "value": 44018.718740068,
            "date": "2017-12-31"
        }, {
            "value": 12353.126829401,
            "date": "2018-01-31"
        }, {
            "value": 12353.126829401,
            "date": "2018-02-28"
        }, {
            "value": 35468.675246247,
            "date": "2018-03-31"
        }, {
            "value": 33948.819039505,
            "date": "2018-04-30"
        }, {
            "value": 40132.212239952,
            "date": "2018-05-31"
        }],
        "itemid": 1093000008,
        "type": 9
    }, {
        "index": 13,
        "itemname": "GFP",
        "children": [{
            "value": 186346.252894263,
            "date": "2017-06-30"
        }, {
            "value": 140820.740406133,
            "date": "2017-07-31"
        }, {
            "value": 148473.895713283,
            "date": "2017-08-31"
        }, {
            "value": 171774.293939526,
            "date": "2017-09-30"
        }, {
            "value": 154091.775383894,
            "date": "2017-10-31"
        }, {
            "value": 166033.906140815,
            "date": "2017-11-30"
        }, {
            "value": 183097.70741524,
            "date": "2017-12-31"
        }, {
            "value": 109559.833386123,
            "date": "2018-01-31"
        }, {
            "value": 112684.160036073,
            "date": "2018-02-28"
        }, {
            "value": 155546.451060079,
            "date": "2018-03-31"
        }, {
            "value": 139032.059229264,
            "date": "2018-04-30"
        }, {
            "value": 151494.76439897,
            "date": "2018-05-31"
        }],
        "itemid": 1093000013,
        "type": 9
    }, {
        "index": 14,
        "itemname": "EXP",
        "children": [{
            "value": 50001.573404053,
            "date": "2017-06-30"
        }, {
            "value": 49265.310996955,
            "date": "2017-07-31"
        }, {
            "value": 50785.653476384,
            "date": "2017-08-31"
        }, {
            "value": 49979.975901749,
            "date": "2017-09-30"
        }, {
            "value": 48270.378167802,
            "date": "2017-10-31"
        }, {
            "value": 54745.479647722,
            "date": "2017-11-30"
        }, {
            "value": 59986.771760345,
            "date": "2017-12-31"
        }, {
            "value": 50736.762255321,
            "date": "2018-01-31"
        }, {
            "value": 43633.287629762,
            "date": "2018-02-28"
        }, {
            "value": 42828.176692789,
            "date": "2018-03-31"
        }, {
            "value": 49470.212400028,
            "date": "2018-04-30"
        }, {
            "value": 52996.080113994,
            "date": "2018-05-31"
        }],
        "itemid": 1093000014,
        "type": 9
    }, {
        "index": 15,
        "itemname": "IMP",
        "children": [{
            "value": 40059.348760731,
            "date": "2017-06-30"
        }, {
            "value": 38486.384651237,
            "date": "2017-07-31"
        }, {
            "value": 41195.642168492,
            "date": "2017-08-31"
        }, {
            "value": 41640.572403625,
            "date": "2017-09-30"
        }, {
            "value": 38396.507917891,
            "date": "2017-10-31"
        }, {
            "value": 44716.081058006,
            "date": "2017-11-30"
        }, {
            "value": 45452.887097028,
            "date": "2017-12-31"
        }, {
            "value": 44634.882542288,
            "date": "2018-01-31"
        }, {
            "value": 36994.138702012,
            "date": "2018-02-28"
        }, {
            "value": 46596.156411204,
            "date": "2018-03-31"
        }, {
            "value": 43414.454169107,
            "date": "2018-04-30"
        }, {
            "value": 47912.722549651,
            "date": "2018-05-31"
        }],
        "itemid": 1093000015,
        "type": 9
    }, {
        "index": 17,
        "itemname": "IC",
        "children": [{
            "value": -34092.463151443,
            "date": "2017-06-30"
        }, {
            "value": 9582.838988546,
            "date": "2017-07-31"
        }, {
            "value": 12590.844823811,
            "date": "2017-08-31"
        }, {
            "value": -7911.968794123,
            "date": "2017-09-30"
        }, {
            "value": -7485.853901164,
            "date": "2017-10-31"
        }, {
            "value": -12966.482006322,
            "date": "2017-11-30"
        }, {
            "value": -24741.12530216,
            "date": "2017-12-31"
        }, {
            "value": 55344.68269945,
            "date": "2018-01-31"
        }, {
            "value": 52080.751617891,
            "date": "2018-02-28"
        }, {
            "value": 17411.70275896,
            "date": "2018-03-31"
        }, {
            "value": 15126.164468006,
            "date": "2018-04-30"
        }, {
            "value": 7580.843918678,
            "date": "2018-05-31"
        }],
        "itemid": 1093000017,
        "type": 9
    }]
}